dictfire/__init__.py
dictfire/__version__.py
dictfire/core.py
dictfire/fake_useragent_v0.1.11.json
dictfire/metadata.py
dictfire/setting.py
dictfire/fire/__init__.py
dictfire/fire/baidu.py
dictfire/fire/bing.py
dictfire/fire/google.py
dictfire/fire/powerword.py
dictfire/fire/youdao.py
dictfire-1.1.20.dist-info/LICENSE
dictfire-1.1.20.dist-info/METADATA
dictfire-1.1.20.dist-info/WHEEL
dictfire-1.1.20.dist-info/entry_points.txt
dictfire-1.1.20.dist-info/top_level.txt
dictfire-1.1.20.dist-info/zip-safe
dictfire-1.1.20.dist-info/RECORD
