Metadata-Version: 2.1
Name: dictfire
Version: 1.1.20
Summary: 命令行下[中英，中俄，中日，中韩，中法，中德，中西]文互翻译工具（Command line translation tool for Chinese English,Chinese French, Chinese Japanese, Chinese Korean, Chinese German），翻译服务基于有道翻译。
Home-page: https://github.com/HeywoodKing/dictfire
Author: hywell
Author-email: opencoding@hotmail.com
Maintainer: hywell
Maintainer-email: opencoding@hotmail.com
License: MIT
Download-URL: https://github.com/HeywoodKing/dictfire
Keywords: Translation English2Chinese,Chinese2English,Chinese2French,French2Chinese,Chinese2Japanese,Japanese2Chinese,Chinese2Korean,Korean2Chinese,Chinese2German,German2Chinese） Command-line
Platform: any
Classifier: Development Status :: 5 - Production/Stable
Classifier: Environment :: Console
Classifier: Intended Audience :: Developers
Classifier: Natural Language :: Chinese (Simplified)
Classifier: Natural Language :: English
Classifier: Topic :: Utilities
Classifier: Topic :: Terminals
Classifier: Topic :: System :: Distributed Computing
Classifier: License :: OSI Approved :: MIT License
Classifier: Programming Language :: Python :: 3
Classifier: Programming Language :: Python :: 3.3
Classifier: Programming Language :: Python :: 3.4
Classifier: Programming Language :: Python :: 3.5
Classifier: Programming Language :: Python :: 3.6
Classifier: Programming Language :: Python :: 3.7
Classifier: Programming Language :: Python :: 3.8
Classifier: Programming Language :: Python :: 3.9
Classifier: Programming Language :: Python :: Implementation :: CPython
Classifier: Programming Language :: Python :: Implementation :: PyPy
Requires-Python: >=3.0.0
Requires-Dist: requests
Requires-Dist: fake-useragent
